ipywidgets_toggle_buttons/__init__.py
ipywidgets_toggle_buttons/abc_toggle_buttons.py
ipywidgets_toggle_buttons/abc_toggle_buttons_with_hide.py
ipywidgets_toggle_buttons/layouts.py
ipywidgets_toggle_buttons/multi_toggle_buttons.py
ipywidgets_toggle_buttons/multi_toggle_buttons_with_hide.py
ipywidgets_toggle_buttons/toggle_buttons_auto_size.py
ipywidgets_toggle_buttons/toggle_buttons_with_hide.py
ipywidgets_toggle_buttons-0.2.3.dist-info/LICENSE.txt
ipywidgets_toggle_buttons-0.2.3.dist-info/WHEEL
ipywidgets_toggle_buttons-0.2.3.dist-info/METADATA
ipywidgets_toggle_buttons-0.2.3.dist-info/RECORD
