Metadata-Version: 2.1
Name: ipywidgets-toggle-buttons
Version: 0.2.3
Summary: PYPI package with better toggle buttons
Home-page: https://github.com/stas-prokopiev/ipywidgets_toggle_buttons
License: MIT
Author: stanislav
Author-email: stas.prokopiev@gmail.com
Requires-Python: >=3.6,<4.0
Classifier: License :: OSI Approved :: MIT License
Classifier: Programming Language :: Python :: 3
Classifier: Programming Language :: Python :: 3.6
Classifier: Programming Language :: Python :: 3.7
Classifier: Programming Language :: Python :: 3.8
Classifier: Programming Language :: Python :: 3.9
Requires-Dist: ipywidgets (>=7.6.3,<8.0.0)
Project-URL: Repository, https://github.com/stas-prokopiev/ipywidgets_toggle_buttons
